daytona_api_client_async/__init__.py
daytona_api_client_async/api_client.py
daytona_api_client_async/api_response.py
daytona_api_client_async/configuration.py
daytona_api_client_async/exceptions.py
daytona_api_client_async/py.typed
daytona_api_client_async/rest.py
daytona_api_client_async/api/__init__.py
daytona_api_client_async/api/admin_api.py
daytona_api_client_async/api/api_keys_api.py
daytona_api_client_async/api/audit_api.py
daytona_api_client_async/api/config_api.py
daytona_api_client_async/api/docker_registry_api.py
daytona_api_client_async/api/health_api.py
daytona_api_client_async/api/jobs_api.py
daytona_api_client_async/api/object_storage_api.py
daytona_api_client_async/api/organizations_api.py
daytona_api_client_async/api/preview_api.py
daytona_api_client_async/api/regions_api.py
daytona_api_client_async/api/runners_api.py
daytona_api_client_async/api/sandbox_api.py
daytona_api_client_async/api/snapshots_api.py
daytona_api_client_async/api/toolbox_api.py
daytona_api_client_async/api/users_api.py
daytona_api_client_async/api/volumes_api.py
daytona_api_client_async/api/webhooks_api.py
daytona_api_client_async/api/workspace_api.py
daytona_api_client_async/models/__init__.py
daytona_api_client_async/models/account_provider.py
daytona_api_client_async/models/admin_create_runner.py
daytona_api_client_async/models/announcement.py
daytona_api_client_async/models/api_key_list.py
daytona_api_client_async/models/api_key_response.py
daytona_api_client_async/models/audit_log.py
daytona_api_client_async/models/build_info.py
daytona_api_client_async/models/command.py
daytona_api_client_async/models/completion_context.py
daytona_api_client_async/models/completion_item.py
daytona_api_client_async/models/completion_list.py
daytona_api_client_async/models/compressed_screenshot_response.py
daytona_api_client_async/models/computer_use_start_response.py
daytona_api_client_async/models/computer_use_status_response.py
daytona_api_client_async-0.138.0.dist-info/licenses/LICENSE
daytona_api_client_async-0.138.0.dist-info/METADATA
daytona_api_client_async-0.138.0.dist-info/WHEEL
daytona_api_client_async-0.138.0.dist-info/top_level.txt
daytona_api_client_async-0.138.0.dist-info/RECORD
